setup.py
drf_mongo_filters/__init__.py
drf_mongo_filters/backend.py
drf_mongo_filters/fields.py
drf_mongo_filters/filters.py
drf_mongo_filters/filtersets.py
drf_mongo_filters.egg-info/PKG-INFO
drf_mongo_filters.egg-info/SOURCES.txt
drf_mongo_filters.egg-info/dependency_links.txt
drf_mongo_filters.egg-info/requires.txt
drf_mongo_filters.egg-info/top_level.txt