Metadata-Version: 1.1
Name: drf-mongo-filters
Version: 1.0
Summary: Filtering support for Django Rest Framework Mongoengine.
Home-page: https://github.com/qwiglydee/drf-mongo-filters
Author: Maxim Vasiliev
Author-email: qwiglydee@gmail.com
License: UNKNOWN
Download-URL: https://github.com/qwiglydee/drf-mongo-filters/releases
Keywords: mongoengine,django rest framework,filtering
Platform: UNKNOWN
Classifier: Development Status :: 4 - Beta
Classifier: Environment :: Web Environment
Classifier: Framework :: Django
Classifier: Intended Audience :: Developers
Classifier: Programming Language :: Python :: 3 :: Only
Classifier: Topic :: Internet :: WWW/HTTP
Classifier: Topic :: Software Development :: Libraries :: Python Modules
